jusfltuls/.bumpversion.cfg
jusfltuls/__init__.py
jusfltuls/check_new_version.py
jusfltuls/cpuspeed.py
jusfltuls/distcheck.py
jusfltuls/distcheck.sh
jusfltuls/dtox.py
jusfltuls/google_tasks.py
jusfltuls/google_tasks_export_file.py
jusfltuls/google_tasks_import.py
jusfltuls/graphtemp.py
jusfltuls/main.py
jusfltuls/mcinfl.py
jusfltuls/mcinfl_library.py
jusfltuls/pingy.py
jusfltuls/pingy2.py
jusfltuls/pycompress.py
jusfltuls/servicesshow.py
jusfltuls/servicesshow.sh
jusfltuls/servicesshow2.py
jusfltuls/skymap.py
jusfltuls/smartnow.py
jusfltuls/smartnow.sh
jusfltuls/smartnow2.py
jusfltuls/sshconf.py
jusfltuls/verif_apt.py
jusfltuls/wavescan.py
jusfltuls/zoter.py
jusfltuls/dev_smanow/commands_and_tests.md
jusfltuls/dev_smanow/non_sudo_commands
jusfltuls/dev_smanow/sudo_commands
jusfltuls-0.3.28.dist-info/METADATA
jusfltuls-0.3.28.dist-info/WHEEL
jusfltuls-0.3.28.dist-info/entry_points.txt
jusfltuls-0.3.28.dist-info/RECORD
