Metadata-Version: 2.4
Name: jusfltuls
Version: 0.3.28
Summary: Userful tools for linux life
Requires-Python: >=3.12
Requires-Dist: blessings>=1.7
Requires-Dist: click>=8.2.0
Requires-Dist: colorclass>=2.2.2
Requires-Dist: console>=0.9911
Requires-Dist: fire>=0.7.0
Requires-Dist: google-api-python-client>=2.176.0
Requires-Dist: google-auth-oauthlib>=1.2.2
Requires-Dist: google>=3.0.0
Requires-Dist: influxdb>=5.3.2
Requires-Dist: matplotlib>=3.10.1
Requires-Dist: numpy>=2.2.5
Requires-Dist: pandas>=2.3.1
Requires-Dist: psutil>=7.0.0
Requires-Dist: pyautogui>=0.9.54
Requires-Dist: pysubs2>=1.8.0
Requires-Dist: srt>=3.5.3
Requires-Dist: terminaltables>=3.1.10
Requires-Dist: unidecode>=1.3.8
Requires-Dist: wifi>=0.3.8
